coincoin/__init__.py
coincoin/kraken.py
coincoin/strategies.py
coincoin/tickers.py
coincoin_goulchen-0.0.13.dist-info/LICENCE
coincoin_goulchen-0.0.13.dist-info/METADATA
coincoin_goulchen-0.0.13.dist-info/WHEEL
coincoin_goulchen-0.0.13.dist-info/top_level.txt
coincoin_goulchen-0.0.13.dist-info/RECORD
