Metadata-Version: 2.1
Name: coincoin-goulchen
Version: 0.0.13
Summary: A small example package
Home-page: UNKNOWN
Author: Goulchen Le Meur
Author-email: author@example.com
License: UNKNOWN
Platform: UNKNOWN
Classifier: Programming Language :: Python :: 3
Classifier: License :: OSI Approved :: MIT License
Classifier: Operating System :: OS Independent
Requires-Python: >=3.6
License-File: LICENCE
Requires-Dist: requests
Requires-Dist: pandas
Requires-Dist: pymongo
Requires-Dist: dill
Requires-Dist: hyperopt
Requires-Dist: bt
Requires-Dist: numpy
